Metadata-Version: 1.1
Name: glue
Version: 0.11.0
Summary: Glue is a simple command line tool to generate sprites.
Home-page: http://github.com/jorgebastida/glue
Author: Jorge Bastida
Author-email: me@jorgebastida.com
License: BSD
Keywords: glue sprites css cocos2d
Platform: any
Classifier: Programming Language :: Python :: 2
Classifier: Programming Language :: Python :: 3
Classifier: Development Status :: 4 - Beta
Classifier: Environment :: Web Environment
Classifier: Intended Audience :: Developers
Classifier: License :: OSI Approved :: BSD License
Classifier: Operating System :: OS Independent
Classifier: Topic :: Utilities
